LICENSE
README.md
setup.py
django_fees.egg-info/PKG-INFO
django_fees.egg-info/SOURCES.txt
django_fees.egg-info/dependency_links.txt
django_fees.egg-info/requires.txt
django_fees.egg-info/top_level.txt
fees/__init__.py
fees/admin.py
fees/apps.py
fees/context_processors.py
fees/cron.py
fees/helpers.py
fees/jobs.py
fees/mixins.py
fees/models.py
fees/querysets.py
fees/settings.py
fees/signals.py
fees/urls.py
fees/views.py
fees/migrations/0001_initial.py
fees/migrations/0002_auto_20220404_2128.py
fees/migrations/0003_auto_20220412_1512.py
fees/migrations/0004_auto_20220412_1513.py
fees/migrations/0005_auto_20220706_1625.py
fees/migrations/0006_auto_20220706_1635.py
fees/migrations/0007_auto_20220706_1652.py
fees/migrations/0008_auto_20220706_1707.py
fees/migrations/0009_auto_20220706_1719.py
fees/migrations/0010_auto_20230223_0008.py
fees/migrations/0011_remove_package_unique_default.py
fees/migrations/__init__.py
fees/templatetags/__init__.py
fees/templatetags/fees.py